setup.cfg
setup.py
delayqueue/__init__.py
delayqueue/core.py
delayqueue.egg-info/PKG-INFO
delayqueue.egg-info/SOURCES.txt
delayqueue.egg-info/dependency_links.txt
delayqueue.egg-info/top_level.txt