Metadata-Version: 1.1
Name: delayqueue
Version: 0.0.3
Summary: Thread-safe delay queue class
Home-page: https://github.com/aisthesis/delayqueue
Author: Marshall Farrier
Author-email: marshalldfarrier@gmail.com
License: UNKNOWN
Download-URL: https://github.com/aisthesis/delayqueue/tarball/0.0.3
Keywords: queue delay thread
Platform: UNKNOWN
Classifier: Development Status :: 4 - Beta
Classifier: Intended Audience :: Developers
Classifier: Intended Audience :: Information Technology
Classifier: License :: OSI Approved
Classifier: License :: OSI Approved :: MIT License
Classifier: Programming Language :: Python
Classifier: Programming Language :: Python :: 3
Classifier: Operating System :: Microsoft :: Windows
Classifier: Operating System :: POSIX
Classifier: Operating System :: Unix
Classifier: Operating System :: MacOS
Classifier: Topic :: Software Development
Classifier: Topic :: Software Development :: Libraries
Classifier: Topic :: Software Development :: Libraries :: Python Modules
